TweetAnalysis/VERSION
TweetAnalysis/__init__.py
TweetAnalysis/config.yml
TweetAnalysis/Config/__init__.py
TweetAnalysis/Config/core.py
TweetAnalysis/Config/logging_config.py
TweetAnalysis/Kafka/.env
TweetAnalysis/Kafka/twitter_api.py
TweetAnalysis/Spark/cassandra.py
TweetAnalysis/Spark/streamer.py
TweetAnalysis/Spark/Text/text_analyzer.py
TweetAnalysis/Spark/Text/text_cleaner.py
TweetAnalysis/Spark/Text/text_processor.py
TweetsAnalysis-1.1.8.dist-info/LICENSE
TweetsAnalysis-1.1.8.dist-info/METADATA
TweetsAnalysis-1.1.8.dist-info/WHEEL
TweetsAnalysis-1.1.8.dist-info/top_level.txt
TweetsAnalysis-1.1.8.dist-info/RECORD
