Metadata-Version: 2.1
Name: TweetsAnalysis
Version: 1.1.8
Summary: Real Time Tweets Analysis.
Home-page: https://github.com/HassanRady/TweetAnalysis
Author: Hassan Rady
Author-email: hassan.khaled.rady@gmail.com
License: MIT license
Keywords: Tweets
Classifier: Development Status :: 2 - Pre-Alpha
Classifier: Intended Audience :: Developers
Classifier: License :: OSI Approved :: MIT License
Classifier: Natural Language :: English
Classifier: Programming Language :: Python :: 3
Classifier: Programming Language :: Python :: 3.6
Classifier: Programming Language :: Python :: 3.7
Classifier: Programming Language :: Python :: 3.8
Requires-Python: >=3.6.0
License-File: LICENSE
Requires-Dist: click
Requires-Dist: Sphinx
Requires-Dist: coverage
Requires-Dist: awscli
Requires-Dist: flake8
Requires-Dist: python-dotenv
Requires-Dist: pathlib2
Requires-Dist: PyArrow
Requires-Dist: langid
Requires-Dist: nltk
Requires-Dist: gensim
Requires-Dist: pandas
Requires-Dist: pyspark
Requires-Dist: kafka-python
Requires-Dist: seaborn
Requires-Dist: tweepy (==3.9.0)
Requires-Dist: pydantic
Requires-Dist: strictyaml
Requires-Dist: joblib
